<annotationInfo>
<annotationInfo>
<item  id="142" filename="fir.cpp" linenumber="30" name="icmp_ln30" contextFuncName="fir" moduleName="fir" rtlName="icmp_ln30_fu_2801_p2" latency="0" BRAM="-1" DSP="-1" FF="0" LUT="11" fileDirectory="C:\9m\HLS\labb\project1\fir128"><\/item>
<item  id="146" filename="fir.cpp" linenumber="31" name="trunc_ln31" contextFuncName="fir" moduleName="fir" rtlName="trunc_ln31_fu_2807_p1" latency="0" BRAM="-1" DSP="-1" FF="-1" LUT="-1" fileDirectory="C:\9m\HLS\labb\project1\fir128"><\/item>
<item  id="147" filename="fir.cpp" linenumber="31" name="add_ln31" contextFuncName="fir" moduleName="fir" rtlName="add_ln31_fu_2811_p2" latency="0" BRAM="-1" DSP="-1" FF="0" LUT="15" fileDirectory="C:\9m\HLS\labb\project1\fir128"><\/item>
<item  id="915" filename="fir.cpp" linenumber="30" name="icmp_ln30_1" contextFuncName="fir" moduleName="fir" rtlName="icmp_ln30_1_fu_3579_p2" latency="0" BRAM="-1" DSP="-1" FF="0" LUT="11" fileDirectory="C:\9m\HLS\labb\project1\fir128"><\/item>
<item  id="918" filename="fir.cpp" linenumber="31" name="add_ln31_1" contextFuncName="fir" moduleName="fir" rtlName="add_ln31_1_fu_3584_p2" latency="0" BRAM="-1" DSP="-1" FF="0" LUT="15" fileDirectory="C:\9m\HLS\labb\project1\fir128"><\/item>
<item  id="1823" filename="fir.cpp" linenumber="37" name="sext_ln37" contextFuncName="fir" moduleName="fir" rtlName="sext_ln37_fu_4357_p1" latency="0" BRAM="-1" DSP="-1" FF="-1" LUT="-1" fileDirectory="C:\9m\HLS\labb\project1\fir128"><\/item>
<item  id="1824" filename="fir.cpp" linenumber="37" name="tmp" contextFuncName="fir" moduleName="fir" rtlName="tmp_fu_4361_p3" latency="0" BRAM="-1" DSP="-1" FF="-1" LUT="-1" fileDirectory="C:\9m\HLS\labb\project1\fir128"><\/item>
<item  id="1829" filename="fir.cpp" linenumber="38" name="zext_ln38" contextFuncName="fir" moduleName="fir" rtlName="zext_ln38_fu_4369_p1" latency="0" BRAM="-1" DSP="-1" FF="-1" LUT="-1" fileDirectory="C:\9m\HLS\labb\project1\fir128"><\/item>
<item  id="1830" filename="fir.cpp" linenumber="38" name="trunc_ln38" contextFuncName="fir" moduleName="fir" rtlName="trunc_ln38_fu_4374_p1" latency="0" BRAM="-1" DSP="-1" FF="-1" LUT="-1" fileDirectory="C:\9m\HLS\labb\project1\fir128"><\/item>
<item  id="2091" filename="fir.cpp" linenumber="38" name="mul_ln38" contextFuncName="fir" moduleName="fir" rtlName="mul_ln38_fu_4387_p2" latency="0" BRAM="-1" DSP="2" FF="0" LUT="20" fileDirectory="C:\9m\HLS\labb\project1\fir128"><\/item>
<item  id="2092" filename="fir.cpp" linenumber="38" name="acc" contextFuncName="fir" moduleName="fir" rtlName="acc_fu_4393_p2" latency="0" BRAM="-1" DSP="-1" FF="0" LUT="39" fileDirectory="C:\9m\HLS\labb\project1\fir128"><\/item>
<item  id="2093" filename="fir.cpp" linenumber="37" name="i" contextFuncName="fir" moduleName="fir" rtlName="i_fu_4378_p2" latency="0" BRAM="-1" DSP="-1" FF="0" LUT="15" fileDirectory="C:\9m\HLS\labb\project1\fir128"><\/item>
<\/annotationInfo>
</annotationInfo>
