{
"fifo_info" : [
{"inst" : "AESL_inst_canny.upperThresh_c_U", "depth" : 1, "input_block" : 0, "output_block" : 0, "work_scenario" : 5, "chan_type" : 2},
{"inst" : "AESL_inst_canny.lowerThresh_c_U", "depth" : 1, "input_block" : 0, "output_block" : 0, "work_scenario" : 5, "chan_type" : 2},
{"inst" : "AESL_inst_canny.x_sobel_V_U", "depth" : 2, "input_block" : 0, "output_block" : 1, "work_scenario" : 3, "chan_type" : 0},
{"inst" : "AESL_inst_canny.y_sobel_V_U", "depth" : 2, "input_block" : 0, "output_block" : 1, "work_scenario" : 3, "chan_type" : 0},
{"inst" : "AESL_inst_canny.y_sobel_7_V_U", "depth" : 2, "input_block" : 0, "output_block" : 1, "work_scenario" : 3, "chan_type" : 0},
{"inst" : "AESL_inst_canny.magnitude_V_U", "depth" : 2, "input_block" : 0, "output_block" : 1, "work_scenario" : 3, "chan_type" : 0},
{"inst" : "AESL_inst_canny.tangent_y_V_U", "depth" : 2, "input_block" : 0, "output_block" : 1, "work_scenario" : 3, "chan_type" : 0},
{"inst" : "AESL_inst_canny.tangent_x_225_V_U", "depth" : 2, "input_block" : 0, "output_block" : 1, "work_scenario" : 3, "chan_type" : 0},
{"inst" : "AESL_inst_canny.tangent_x_675_V_U", "depth" : 2, "input_block" : 0, "output_block" : 1, "work_scenario" : 3, "chan_type" : 0},
],
"lat_total" : 17459
}
